fastapi_ronin/__init__.py
fastapi_ronin/decorators.py
fastapi_ronin/defaults.py
fastapi_ronin/generics.py
fastapi_ronin/lookups.py
fastapi_ronin/mixins.py
fastapi_ronin/pagination.py
fastapi_ronin/permissions.py
fastapi_ronin/routes.py
fastapi_ronin/schemas.py
fastapi_ronin/state.py
fastapi_ronin/types.py
fastapi_ronin/validation.py
fastapi_ronin/viewsets.py
fastapi_ronin/wrappers.py
fastapi_ronin/cache/__init__.py
fastapi_ronin/cache/base.py
fastapi_ronin/cache/cache.py
fastapi_ronin/cache/cache_client_interface.py
fastapi_ronin/cache/memory.py
fastapi_ronin/cache/redis.py
fastapi_ronin/filters/__init__.py
fastapi_ronin/filters/filters.py
fastapi_ronin/filters/lookups.py
fastapi_ronin-0.4.2.dist-info/METADATA
fastapi_ronin-0.4.2.dist-info/WHEEL
fastapi_ronin-0.4.2.dist-info/licenses/LICENSE
fastapi_ronin-0.4.2.dist-info/RECORD
