Metadata-Version: 2.4
Name: fastapi-ronin
Version: 0.4.2
Summary: FastAPI Ronin is a library for building FastAPI applications with a Django REST Framework-inspired architecture.
Project-URL: Documentation, https://github.com/bubaley/fastapi-ronin#readme
Project-URL: Homepage, https://github.com/bubaley/fastapi-ronin
Project-URL: Repository, https://github.com/bubaley/fastapi-ronin.git
Author-email: bubaley <bubaley.fu@gmail.com>
Maintainer-email: bubaley <bubaley.fu@gmail.com>
License: MIT
License-File: LICENSE
Keywords: django,django-rest-framework,fastapi,pagination,tortoise,viewsets
Classifier: Development Status :: 4 - Beta
Classifier: Framework :: FastAPI
Classifier: Intended Audience :: Developers
Classifier: License :: OSI Approved :: MIT License
Classifier: Programming Language :: Python :: 3 :: Only
Classifier: Programming Language :: Python :: 3.12
Classifier: Programming Language :: Python :: 3.13
Classifier: Topic :: Internet :: WWW/HTTP
Classifier: Topic :: Software Development :: Libraries :: Python Modules
Classifier: Typing :: Typed
Requires-Python: <3.14,>=3.12
Requires-Dist: fastapi>=0.115.13
Requires-Dist: tortoise-orm>=0.25.1
